logger/__init__.py
logger/logger.py
wb_logger-0.0.1.dist-info/METADATA
wb_logger-0.0.1.dist-info/WHEEL
wb_logger-0.0.1.dist-info/licenses/LICENSE
wb_logger-0.0.1.dist-info/RECORD
