Metadata-Version: 2.4
Name: wb-logger
Version: 0.0.1
Summary: 
License-File: LICENSE
Author: mathewgeola
Author-email: mathewgeola@gmail.com
Requires-Python: >=3.12
Classifier: Programming Language :: Python :: 3
Classifier: Programming Language :: Python :: 3.12
Classifier: Programming Language :: Python :: 3.13
Classifier: Programming Language :: Python :: 3.14
Requires-Dist: colorlog (>=6.10.1,<7.0.0)
